asynchronous_requests/__init__.py
asynchronous_requests/adapters.py
asynchronous_requests/api.py
asynchronous_requests/asgi.py
asynchronous_requests/cookies.py
asynchronous_requests/exceptions.py
asynchronous_requests/models.py
asynchronous_requests/sessions.py
asynchronous_requests/status_codes.py
asynchronous_requests-0.6.2.data/data/LICENSE.md
asynchronous_requests-0.6.2.dist-info/LICENSE.md
asynchronous_requests-0.6.2.dist-info/METADATA
asynchronous_requests-0.6.2.dist-info/WHEEL
asynchronous_requests-0.6.2.dist-info/top_level.txt
asynchronous_requests-0.6.2.dist-info/RECORD
