Metadata-Version: 2.1
Name: asynchronous-requests
Version: 0.6.2
Summary: async-await support for `requests`.
Home-page: https://github.com/encode/requests-async
Author: Tom Christie
Author-email: tom@tomchristie.com
License: BSD
Classifier: Development Status :: 3 - Alpha
Classifier: Environment :: Web Environment
Classifier: Intended Audience :: Developers
Classifier: License :: OSI Approved :: BSD License
Classifier: Operating System :: OS Independent
Classifier: Topic :: Internet :: WWW/HTTP
Classifier: Programming Language :: Python :: 3
Classifier: Programming Language :: Python :: 3.6
Classifier: Programming Language :: Python :: 3.7
Classifier: Programming Language :: Python :: 3.8
Requires-Python: >=3.6
License-File: LICENSE.md
Requires-Dist: requests (==2.*)
Requires-Dist: http3 (==0.6.*)
